{
  "auti": 1,
  "kuce": 66,
  "stanovi": 78,
  "_stats": {
    "date": "2026-06-28",
    "total_runs": 3,
    "successful_scrapes": {
      "nj_auti": 3,
      "nj_kuce": 3,
      "nj_stanovi": 3,
      "idx_auti": 3,
      "idx_kuce": 3,
      "idx_stanovi": 3,
      "oglas_stanovi": 3,
      "oglas_kuce": 3,
      "bj_stanovi": 3,
      "bj_kuce": 3
    },
    "failed_scrapes": {},
    "last_report_counts": {
      "auti": 1,
      "kuce": 66,
      "stanovi": 78,
      "nj_auti": 3,
      "nj_kuce": 75,
      "nj_stanovi": 103,
      "idx_stanovi": 66,
      "idx_auti": 1,
      "idx_kuce": 38,
      "oglas_stanovi": 52,
      "oglas_kuce": 23,
      "bj_stanovi": 13,
      "bj_kuce": 17
    },
    "report_sent": false
  },
  "nj_auti": 3,
  "nj_kuce": 75,
  "nj_stanovi": 103,
  "idx_stanovi": 66,
  "idx_auti": 1,
  "idx_kuce": 38,
  "oglas_stanovi": 52,
  "oglas_kuce": 23,
  "bj_stanovi": 13,
  "bj_kuce": 17
}
